{
  "id": "1747915795333",
  "title": "Ad Fatigue: Why Your Ads Are Losing Impact & How to Fix It",
  "slug": "ad-fatigue-why-your-ads-are-losing-impact-how-to-fix-it",
  "excerpt": "ShootOrder | Digital Marketing Agency, a division of Ivent It Solutions Pvt. Ltd., is a privately held digital marketing company in hyderabad, India. From conception we made sure that we set our foot into the massive universe of internet ventures which we knew the best and since then we have been making strides towards creative innovative and strategic benchmarks across the realm of digital marketing, with an adept talent pool and hunger for perfection we have been delivering the best results, bringing new market trends and have bought in more business for all our clients.",
  "content": "<p>\nWe love our work, yes that's the simplest way to describe why we have been thriving in our business, and serving our global clientele without a glitch or sense of dissatisfaction in our services.\n</p>",
  "author": "shootorder",
  "imageUrl": "/images/blogs/1747915772900-9i3vrbzcdx.png",
  "tags": [
    "hyderabad",
    "shootorder",
    "ivent"
  ],
  "category": "marketing",
  "published": true,
  "publishDate": "2025-05-22T00:00:00.000Z",
  "createdAt": "2025-05-22T12:09:55.333Z",
  "updatedAt": "2025-05-22T12:09:55.333Z",
  "views": 0,
  "likes": 0
}